cirkit.cpython-35m-darwin.so
cirkit-3.0a2.dev3.dist-info/METADATA
cirkit-3.0a2.dev3.dist-info/RECORD
cirkit-3.0a2.dev3.dist-info/WHEEL
cirkit-3.0a2.dev3.dist-info/top_level.txt
