Metadata-Version: 1.1
Name: cirkit
Version: 3.0a2.dev3
Summary: A C++ logic synthesis framework
Home-page: https://msoeken.github.io/cirkit.html
Author: Mathias Soeken
Author-email: mathias.soeken@epfl.ch
License: UNKNOWN
Platform: UNKNOWN
Classifier: License :: OSI Approved :: MIT License
Classifier: Operating System :: OS Independent
